expai/__init__.py
expai/constants.py
expai/expai_explainer.py
expai/expai_explanation.py
expai/expai_fairness.py
expai/expai_performance.py
expai/expai_project.py
expai/expai_requests.py
expai/test_main.py
expai/utils.py
expai-1.4.6.dist-info/LICENSE.txt
expai-1.4.6.dist-info/METADATA
expai-1.4.6.dist-info/WHEEL
expai-1.4.6.dist-info/top_level.txt
expai-1.4.6.dist-info/RECORD
