Metadata-Version: 2.1
Name: expai
Version: 1.4.6
Summary: User-friendly library to interact with EXPAI
Home-page: https://expai.io
Author: EXPAI
Author-email: info@expai.io
License: MIT
Download-URL: https://pypi.org/project/expai/
Keywords: EXPAI,ExplainableAI,Explainable Artificial Intelligence
Platform: UNKNOWN
License-File: LICENSE.txt
Requires-Dist: requests
Requires-Dist: ipython
Requires-Dist: pandas
Requires-Dist: numpy
Requires-Dist: plotly
